SOLARNET/Data.py
SOLARNET/Dataset.py
SOLARNET/Datasets.py
SOLARNET/__init__.py
SOLARNET/api.py
SOLARNET/filters.py
SOLARNET/time.py
SOLARNET-2.2.dist-info/LICENSE
SOLARNET-2.2.dist-info/METADATA
SOLARNET-2.2.dist-info/WHEEL
SOLARNET-2.2.dist-info/top_level.txt
SOLARNET-2.2.dist-info/RECORD
