Metadata-Version: 2.1
Name: SOLARNET
Version: 2.2
Summary: A python 3 client to access the RESTfull API of the SOLARNET Virtual Observatory
Home-page: https://github.com/bmampaey/SOLARNET-python-client
Author: Benjamin Mampaey
Author-email: bmampaey@gmail.com
License: MIT
Download-URL: https://github.com/bmampaey/SOLARNET-python-client/tarball/2.2
Keywords: sun,astronomy,SOLARNET,RESTful
Platform: any
Classifier: Development Status :: 5 - Production/Stable
Classifier: Intended Audience :: Science/Research
Classifier: License :: OSI Approved :: MIT License
Classifier: Natural Language :: English
Classifier: Operating System :: OS Independent
Classifier: Programming Language :: Python :: 3
Classifier: Topic :: Scientific/Engineering :: Astronomy
Requires-Python: >=3.4
License-File: LICENSE
Requires-Dist: python-dateutil
Requires-Dist: slumber
Requires-Dist: astropy
